{
	"__comment": "Designed by Hialus with Cubik Studio - https://cubik.studio",
	"textures": {
		"texture": "voodoo:item/needle"
	},
	"elements": [ 	 
		{
			"__comment": "Voxels-AAAAAA",
			"from": [ 7.75, 6.625, 7.875 ],
			"to": [ 7.875, 7.125, 8.125 ],
			"faces": {
				"down": { "uv": [ 4.96, 0.96, 7.04, 3.04 ], "texture": "#texture" },
				"up": { "uv": [ 4.96, 0.96, 7.04, 3.04 ], "texture": "#texture" },
				"north": { "uv": [ 4.96, 0.96, 7.04, 3.04 ], "texture": "#texture" },
				"south": { "uv": [ 4.96, 0.96, 7.04, 3.04 ], "texture": "#texture" },
				"west": { "uv": [ 4.96, 0.96, 7.04, 3.04 ], "texture": "#texture" },
				"east": { "uv": [ 4.96, 0.96, 7.04, 3.04 ], "texture": "#texture" }
			}
		},
		{
			"__comment": "Voxels-AAAAAA",
			"from": [ 7.875, 0, 7.875 ],
			"to": [ 8, 0.25, 8 ],
			"faces": {
				"down": { "uv": [ 4.96, 0.96, 7.04, 3.04 ], "texture": "#texture" },
				"up": { "uv": [ 4.96, 0.96, 7.04, 3.04 ], "texture": "#texture" },
				"north": { "uv": [ 4.96, 0.96, 7.04, 3.04 ], "texture": "#texture" },
				"south": { "uv": [ 4.96, 0.96, 7.04, 3.04 ], "texture": "#texture" },
				"west": { "uv": [ 4.96, 0.96, 7.04, 3.04 ], "texture": "#texture" },
				"east": { "uv": [ 4.96, 0.96, 7.04, 3.04 ], "texture": "#texture" }
			}
		},
		{
			"__comment": "Voxels-AAAAAA",
			"from": [ 7.875, 0.125, 8 ],
			"to": [ 8, 0.25, 8.125 ],
			"faces": {
				"down": { "uv": [ 4.96, 0.96, 7.04, 3.04 ], "texture": "#texture" },
				"up": { "uv": [ 4.96, 0.96, 7.04, 3.04 ], "texture": "#texture" },
				"north": { "uv": [ 4.96, 0.96, 7.04, 3.04 ], "texture": "#texture" },
				"south": { "uv": [ 4.96, 0.96, 7.04, 3.04 ], "texture": "#texture" },
				"west": { "uv": [ 4.96, 0.96, 7.04, 3.04 ], "texture": "#texture" },
				"east": { "uv": [ 4.96, 0.96, 7.04, 3.04 ], "texture": "#texture" }
			}
		},
		{
			"__comment": "Voxels-AAAAAA",
			"from": [ 7.875, 0.25, 7.875 ],
			"to": [ 8.125, 6.625, 8.125 ],
			"faces": {
				"down": { "uv": [ 4.96, 0.96, 7.04, 3.04 ], "texture": "#texture" },
				"up": { "uv": [ 4.96, 0.96, 7.04, 3.04 ], "texture": "#texture" },
				"north": { "uv": [ 4.96, 0.96, 7.04, 3.04 ], "texture": "#texture" },
				"south": { "uv": [ 4.96, 0.96, 7.04, 3.04 ], "texture": "#texture" },
				"west": { "uv": [ 4.96, 0.96, 7.04, 3.04 ], "texture": "#texture" },
				"east": { "uv": [ 4.96, 0.96, 7.04, 3.04 ], "texture": "#texture" }
			}
		},
		{
			"__comment": "Voxels-AAAAAA",
			"from": [ 7.875, 7.125, 7.875 ],
			"to": [ 8.125, 7.25, 8.125 ],
			"faces": {
				"down": { "uv": [ 4.96, 0.96, 7.04, 3.04 ], "texture": "#texture" },
				"up": { "uv": [ 4.96, 0.96, 7.04, 3.04 ], "texture": "#texture" },
				"north": { "uv": [ 4.96, 0.96, 7.04, 3.04 ], "texture": "#texture" },
				"south": { "uv": [ 4.96, 0.96, 7.04, 3.04 ], "texture": "#texture" },
				"west": { "uv": [ 4.96, 0.96, 7.04, 3.04 ], "texture": "#texture" },
				"east": { "uv": [ 4.96, 0.96, 7.04, 3.04 ], "texture": "#texture" }
			}
		},
		{
			"__comment": "Voxels-AAAAAA",
			"from": [ 8, 0.125, 7.875 ],
			"to": [ 8.125, 0.25, 8 ],
			"faces": {
				"down": { "uv": [ 4.96, 0.96, 7.04, 3.04 ], "texture": "#texture" },
				"up": { "uv": [ 4.96, 0.96, 7.04, 3.04 ], "texture": "#texture" },
				"north": { "uv": [ 4.96, 0.96, 7.04, 3.04 ], "texture": "#texture" },
				"south": { "uv": [ 4.96, 0.96, 7.04, 3.04 ], "texture": "#texture" },
				"west": { "uv": [ 4.96, 0.96, 7.04, 3.04 ], "texture": "#texture" },
				"east": { "uv": [ 4.96, 0.96, 7.04, 3.04 ], "texture": "#texture" }
			}
		},
		{
			"__comment": "Voxels-AAAAAA",
			"from": [ 8.125, 6.625, 7.875 ],
			"to": [ 8.25, 7.125, 8.125 ],
			"faces": {
				"down": { "uv": [ 4.96, 0.96, 7.04, 3.04 ], "texture": "#texture" },
				"up": { "uv": [ 4.96, 0.96, 7.04, 3.04 ], "texture": "#texture" },
				"north": { "uv": [ 4.96, 0.96, 7.04, 3.04 ], "texture": "#texture" },
				"south": { "uv": [ 4.96, 0.96, 7.04, 3.04 ], "texture": "#texture" },
				"west": { "uv": [ 4.96, 0.96, 7.04, 3.04 ], "texture": "#texture" },
				"east": { "uv": [ 4.96, 0.96, 7.04, 3.04 ], "texture": "#texture" }
			}
		}
	],
	"display": {
		"thirdperson_righthand": {
			"rotation":  [ 180, 0, 0 ],
			"translation":  [ 0, -1, 2 ]
		},
		"thirdperson_lefthand": {
			"rotation":  [ 180, 0, 0 ],
			"translation":  [ 0, -1, 2 ]
		},
		"firstperson_righthand": {
			"rotation":  [ 139, -161, 3 ],
			"translation":  [ -2, 3, 5 ]
		},
		"firstperson_lefthand": {
			"rotation":  [ 139, -161, 3 ],
			"translation":  [ -2, 3, 5 ]
		},
		"gui": {
			"rotation":  [ 20, 20, -40 ],
			"translation":  [ 4, 6, 0 ],
			"scale":  [ 2, 2, 2 ]
		},
		"head": {
			"rotation":  [ 22, 0, 27 ],
			"translation":  [ -8.347, 12, 6.9565 ]
		},
		"ground": {
			"rotation":  [ 90, 0, 0 ],
			"translation":  [ 0, 0, 5 ]
		},
		"fixed": {
			"translation":  [ 0, 8, 0 ],
			"scale":  [ 2, 2, 2 ]
		}
	}
}